Metadata-Version: 1.0
Name: ukpocopy
Version: 0.2.0
Summary: A python package for UK Postcode validation and formatting.
Home-page: http://github.com/sephioh/ukpocopy
Author: Abraão Alcântara
Author-email: sephioh@gmail.com
License: MIT
Platform: UNKNOWN
